<?xml version="1.0" encoding="UTF-8"?>
<vocabulary-card lang="es">
  <vc_card-1 day="1">
    <vc_card-1_front>
      <graphic href="EC3-5_VC_Eng_Lang_T6W01D1_C1_1124208161_cropped.png"/>
      <section-block type="f_1" index="1">
        <vc_front_vocab-word>apareció</vc_front_vocab-word>
      </section-block>
    </vc_card-1_front>
    <vc_card-1_back>
      <masthead>
        <section-block type="masthead_b_1" index="1">
          <vc_back_component_header>vocabulario</vc_back_component_header>
        </section-block>
      </masthead>
      <introduce-section>
        <section-block type="introduce_b_1" index="1">
          <vc_back_b-hed>apareció   </vc_back_b-hed>
          <vc_back_c-hed>Repita</vc_back_c-hed>
          <vc_back_teacher-talk>Repitan esta palabra: <vc_teacher-talk-emphasis_non-ital>apareció</vc_teacher-talk-emphasis_non-ital>.</vc_back_teacher-talk>
          <vc_back_c-hed>Defina </vc_back_c-hed>
          <vc_back_teacher-talk>Si algo apareció, es que no se veía y de pronto se pudo ver.</vc_back_teacher-talk>
          <vc_back_c-hed>Describa </vc_back_c-hed>
          <vc_back_teacher-talk>El niño apareció por la esquina. </vc_back_teacher-talk>
          <vc_back_c-hed>Represente</vc_back_c-hed>
          <vc_back_teacher-talk>¿Pueden hacer aparecer un codo? ¿Pueden hacer aparecer cinco dedos?   </vc_back_teacher-talk>
        </section-block>
      </introduce-section>
      <reteach-section>
        <section-block type="reteach_b_1" index="1">
          <vc_back_b-hed>apareció   </vc_back_b-hed>
          <vc_back_c-hed>Repita</vc_back_c-hed>
          <vc_back_teacher-talk>Repitan esta palabra: <vc_teacher-talk-emphasis_non-ital>apareció</vc_teacher-talk-emphasis_non-ital>.</vc_back_teacher-talk>
          <vc_back_c-hed>Defina </vc_back_c-hed>
          <vc_back_teacher-talk>Si algo apareció, es que no se veía y de pronto se pudo ver.</vc_back_teacher-talk>
          <vc_back_c-hed>Converse</vc_back_c-hed>
          <vc_back_teacher-talk>¿Cómo se sintieron alguna vez que jugaban a los escondidos y apareció el niño que los buscaba y los encontró? </vc_back_teacher-talk>
          <vc_teacher-card_body>Repita, reformule o amplíe.</vc_teacher-card_body>
        </section-block>
      </reteach-section>
      <copyright-section>
        <section-block type="copyright_b_1" index="1">
          <vc_back_copyright-line>
            <isbn>978-1-338-66281-8</isbn>. TM ® &amp; © Scholastic Inc. All rights reserved. © Vitec/Shutterstock. </vc_back_copyright-line>
        </section-block>
      </copyright-section>
    </vc_card-1_back>
  </vc_card-1>
  <vc_card-2 day="1">
    <vc_card-2_front>
      <graphic href="EC3-5_VC_Spa_Lang_T6W01D1_C2_184223570_cropped.png"/>
      <section-block type="f_2" index="1">
        <vc_front_vocab-word>se posaron</vc_front_vocab-word>
      </section-block>
    </vc_card-2_front>
    <vc_card-2_back>
      <masthead>
        <section-block type="masthead_b_2" index="1">
          <vc_back_component_header>vocabulario</vc_back_component_header>
        </section-block>
      </masthead>
      <introduce-section>
        <section-block type="introduce_b_2" index="1">
          <vc_back_b-hed>se posaron    </vc_back_b-hed>
          <vc_back_c-hed>Repita </vc_back_c-hed>
          <vc_back_teacher-talk>Repitan estas palabras: <vc_teacher-talk-emphasis_non-ital>se posaron</vc_teacher-talk-emphasis_non-ital>.</vc_back_teacher-talk>
          <vc_back_c-hed>Defina </vc_back_c-hed>
          <vc_back_teacher-talk>Posarse significa pararse en un lugar después de haber volado.</vc_back_teacher-talk>
          <vc_back_c-hed>Describa</vc_back_c-hed>
          <vc_back_teacher-talk>Los pájaros de la imagen se posaron sobre una rama.  </vc_back_teacher-talk>
          <vc_back_c-hed>Represente</vc_back_c-hed>
          <vc_back_teacher-talk>Imaginemos que nuestras manos son pájaros. Simulemos que vuelan y luego se posan sobre la mesa.</vc_back_teacher-talk>
        </section-block>
      </introduce-section>
      <reteach-section>
        <section-block type="reteach_b_2" index="1">
          <vc_back_b-hed>se posaron    </vc_back_b-hed>
          <vc_back_c-hed>Repita</vc_back_c-hed>
          <vc_back_teacher-talk>Repitan estas palabras: <vc_teacher-talk-emphasis_non-ital>se posaron</vc_teacher-talk-emphasis_non-ital>.</vc_back_teacher-talk>
          <vc_back_c-hed>Defina </vc_back_c-hed>
          <vc_back_teacher-talk>Posarse significa pararse en un lugar después de haber volado.</vc_back_teacher-talk>
          <vc_back_c-hed>Converse </vc_back_c-hed>
          <vc_back_teacher-talk>Miren la imagen. ¿Qué creen que ven los pájaros desde la rama en la que se posaron? </vc_back_teacher-talk>
          <vc_teacher-card_body>Repita, reformule o amplíe.</vc_teacher-card_body>
        </section-block>
      </reteach-section>
      <copyright-section>
        <section-block type="copyright_b_2" index="1">
          <vc_back_copyright-line>
            <isbn>978-1-338-66281-8</isbn>. TM ® &amp; © Scholastic Inc. All rights reserved. © Eric Isselee/Shutterstock.</vc_back_copyright-line>
        </section-block>
      </copyright-section>
    </vc_card-2_back>
  </vc_card-2>
  <vc_card-3 day="2">
    <vc_card-3_front>
      <graphic href="EC3-5_VC_Spa_Lang_T6W01D2_C1_658656685_cropped.png"/>
      <section-block type="f_3" index="1">
        <vc_front_vocab-word>tararear</vc_front_vocab-word>
      </section-block>
    </vc_card-3_front>
    <vc_card-3_back>
      <masthead>
        <section-block type="masthead_b_3" index="1">
          <vc_back_component_header>vocabulario</vc_back_component_header>
        </section-block>
      </masthead>
      <introduce-section>
        <section-block type="introduce_b_3" index="1">
          <vc_back_b-hed_horiz>tararear   </vc_back_b-hed_horiz>
          <vc_back_c-hed>Repita</vc_back_c-hed>
          <vc_back_teacher-talk_horiz>Repitan esta palabra: <vc_teacher-talk-emphasis_non-ital>tararear</vc_teacher-talk-emphasis_non-ital>.</vc_back_teacher-talk_horiz>
          <vc_back_c-hed>Defina </vc_back_c-hed>
          <vc_back_teacher-talk_horiz>Cuando tararean cantan una canción en voz baja y sin decir todas las palabras.</vc_back_teacher-talk_horiz>
          <vc_back_c-hed>Describa </vc_back_c-hed>
          <vc_back_teacher-talk_horiz>El papá tararea una canción mientras duerme a su bebé. ¿Por qué creen que tararea en lugar de cantar?</vc_back_teacher-talk_horiz>
          <vc_back_c-hed>Represente</vc_back_c-hed>
          <vc_back_teacher-talk_horiz>¿Quién puede mostrarnos cómo tararea su canción favorita?  </vc_back_teacher-talk_horiz>
        </section-block>
      </introduce-section>
      <reteach-section>
        <section-block type="reteach_b_3" index="1">
          <vc_back_b-hed_horiz>tararear   </vc_back_b-hed_horiz>
          <vc_back_c-hed>Repita</vc_back_c-hed>
          <vc_back_teacher-talk_horiz>Repitan esta palabra: <vc_teacher-talk-emphasis_non-ital>tararear</vc_teacher-talk-emphasis_non-ital>.</vc_back_teacher-talk_horiz>
          <vc_back_c-hed>Defina </vc_back_c-hed>
          <vc_back_teacher-talk_horiz>Cuando tararean cantan una canción en voz baja y sin decir todas las palabras.</vc_back_teacher-talk_horiz>
          <vc_back_c-hed>Converse </vc_back_c-hed>
          <vc_back_teacher-talk_horiz>¿En qué momento podrían tararear una canción? ¿Pueden decirnos por qué?  </vc_back_teacher-talk_horiz>
          <vc_teacher-card_body>Repita, reformule o amplíe.</vc_teacher-card_body>
        </section-block>
      </reteach-section>
      <copyright-section>
        <section-block type="copyright_b_3" index="1">
          <vc_back_copyright-line>
            <isbn>978-1-338-66281-8</isbn>. TM ® &amp; © Scholastic Inc. All rights reserved. © Zoteva/Shutterstock.</vc_back_copyright-line>
        </section-block>
      </copyright-section>
    </vc_card-3_back>
  </vc_card-3>
  <vc_card-4 day="2">
    <vc_card-4_front>
      <graphic href="EC3-5_VC_Eng_Lang_T6W01D2_C2_267710471_cropped.png"/>
      <section-block type="f_4" index="1">
        <vc_front_vocab-word>conflicto</vc_front_vocab-word>
      </section-block>
    </vc_card-4_front>
    <vc_card-4_back>
      <masthead>
        <section-block type="masthead_b_4" index="1">
          <vc_back_component_header>vocabulario</vc_back_component_header>
        </section-block>
      </masthead>
      <introduce-section>
        <section-block type="introduce_b_4" index="1">
          <vc_back_b-hed>conflicto   </vc_back_b-hed>
          <vc_back_c-hed>Repita</vc_back_c-hed>
          <vc_back_teacher-talk>Repitan esta palabra: <vc_teacher-talk-emphasis_non-ital>conflicto</vc_teacher-talk-emphasis_non-ital>.</vc_back_teacher-talk>
          <vc_back_c-hed>Defina </vc_back_c-hed>
          <vc_back_teacher-talk>Un conflicto ocurre cuando las personas no están de acuerdo sobre algo.</vc_back_teacher-talk>
          <vc_back_c-hed>Describa </vc_back_c-hed>
          <vc_back_teacher-talk>Estos hermanos tienen un conflicto. Observando sus caras y sus cuerpos, se puede ver que no están de acuerdo.</vc_back_teacher-talk>
          <vc_back_c-hed>Represente</vc_back_c-hed>
          <vc_back_teacher-talk>Muéstrenme cómo están ustedes cuando tienen un conflicto con alguien. Represéntenlo con la cara y el cuerpo.   </vc_back_teacher-talk>
        </section-block>
      </introduce-section>
      <reteach-section>
        <section-block type="reteach_b_4" index="1">
          <vc_back_b-hed>conflicto   </vc_back_b-hed>
          <vc_back_c-hed>Repita</vc_back_c-hed>
          <vc_back_teacher-talk>Repitan esta palabra: <vc_teacher-talk-emphasis_non-ital>conflicto</vc_teacher-talk-emphasis_non-ital>.</vc_back_teacher-talk>
          <vc_back_c-hed>Defina </vc_back_c-hed>
          <vc_back_teacher-talk>Un conflicto ocurre cuando las personas no están de acuerdo sobre algo.</vc_back_teacher-talk>
          <vc_back_c-hed>Converse </vc_back_c-hed>
          <vc_back_teacher-talk>Esta imagen muestra dos personas que tienen un conflicto. ¿Sobre qué creen que es el conflicto? </vc_back_teacher-talk>
          <vc_teacher-card_body>Repita, reformule o amplíe.</vc_teacher-card_body>
        </section-block>
      </reteach-section>
      <copyright-section>
        <section-block type="copyright_b_4" index="1">
          <vc_back_copyright-line>
            <isbn>978-1-338-66281-8</isbn>. TM ® &amp; © Scholastic Inc. All rights reserved. © Granata68/Shutterstock.</vc_back_copyright-line>
        </section-block>
      </copyright-section>
    </vc_card-4_back>
  </vc_card-4>
  <vc_card-5 day="3">
    <vc_card-5_front>
      <graphic href="EC3-5_VC_Eng_Lang_T6W01D3_C1_117531202_cropped.png"/>
      <section-block type="f_5" index="1">
        <vc_front_vocab-word>congregarse</vc_front_vocab-word>
      </section-block>
    </vc_card-5_front>
    <vc_card-5_back>
      <masthead>
        <section-block type="masthead_b_5" index="1">
          <vc_back_component_header>vocabulario</vc_back_component_header>
        </section-block>
      </masthead>
      <introduce-section>
        <section-block type="introduce_b_5" index="1">
          <vc_back_b-hed_horiz>congregarse   </vc_back_b-hed_horiz>
          <vc_back_c-hed>Repita</vc_back_c-hed>
          <vc_back_teacher-talk_horiz>Repitan esta palabra: <vc_teacher-talk-emphasis_non-ital>congregarse</vc_teacher-talk-emphasis_non-ital>.</vc_back_teacher-talk_horiz>
          <vc_back_c-hed>Defina </vc_back_c-hed>
          <vc_back_teacher-talk_horiz>Las personas se congregan cuando se reúnen en un lugar.</vc_back_teacher-talk_horiz>
          <vc_back_c-hed>Describa </vc_back_c-hed>
          <vc_back_teacher-talk_horiz>Se congregaron muchas personas para ver el espectáculo.</vc_back_teacher-talk_horiz>
          <vc_back_c-hed>Represente</vc_back_c-hed>
          <vc_back_teacher-talk_horiz>Vamos a pararnos y luego vamos a congregarnos junto a la pizarra. </vc_back_teacher-talk_horiz>
        </section-block>
      </introduce-section>
      <reteach-section>
        <section-block type="reteach_b_5" index="1">
          <vc_back_b-hed_horiz>congregarse   </vc_back_b-hed_horiz>
          <vc_back_c-hed>Repita</vc_back_c-hed>
          <vc_back_teacher-talk_horiz>Repitan esta palabra: <vc_teacher-talk-emphasis_non-ital>congregarse</vc_teacher-talk-emphasis_non-ital>.</vc_back_teacher-talk_horiz>
          <vc_back_c-hed>Defina </vc_back_c-hed>
          <vc_back_teacher-talk_horiz>Las personas se congregan cuando se reúnen en un lugar.</vc_back_teacher-talk_horiz>
          <vc_back_c-hed>Converse </vc_back_c-hed>
          <vc_back_teacher-talk_horiz>Esta imagen muestra muchas personas congregadas para ver el espectáculo de los niños. ¿En qué otro lugar podría congregarse la gente?</vc_back_teacher-talk_horiz>
          <vc_teacher-card_body>Repita, reformule o amplíe.</vc_teacher-card_body>
        </section-block>
      </reteach-section>
      <copyright-section>
        <section-block type="copyright_b_5" index="1">
          <vc_back_copyright-line>
            <isbn>978-1-338-66281-8</isbn>. TM ® &amp; © Scholastic Inc. All rights reserved. © Faraways/Shutterstock.</vc_back_copyright-line>
        </section-block>
      </copyright-section>
    </vc_card-5_back>
  </vc_card-5>
  <vc_card-6 day="3">
    <vc_card-6_front>
      <graphic href="EC3-5_VC_Eng_Lang_T6W01D3_C2_1024050373_cropped.png"/>
      <section-block type="f_6" index="1">
        <vc_front_vocab-word>silencioso</vc_front_vocab-word>
      </section-block>
    </vc_card-6_front>
    <vc_card-6_back>
      <masthead>
        <section-block type="masthead_b_6" index="1">
          <vc_back_component_header>vocabulario</vc_back_component_header>
        </section-block>
      </masthead>
      <introduce-section>
        <section-block type="introduce_b_6" index="1">
          <vc_back_b-hed>silencioso   </vc_back_b-hed>
          <vc_back_c-hed>Repita</vc_back_c-hed>
          <vc_back_teacher-talk>Repitan esta palabra: <vc_teacher-talk-emphasis_non-ital>silencioso</vc_teacher-talk-emphasis_non-ital>.</vc_back_teacher-talk>
          <vc_back_c-hed>Defina </vc_back_c-hed>
          <vc_back_teacher-talk>Cuando están silenciosos hacen muy poco ruido.</vc_back_teacher-talk>
          <vc_back_c-hed>Describa </vc_back_c-hed>
          <vc_back_teacher-talk>Cuando están en la biblioteca tienen que ser silenciosos.</vc_back_teacher-talk>
          <vc_back_c-hed>Represente</vc_back_c-hed>
          <vc_back_teacher-talk>Muéstrenme cómo podemos decirle a alguien que sea silencioso.  </vc_back_teacher-talk>
        </section-block>
      </introduce-section>
      <reteach-section>
        <section-block type="reteach_b_6" index="1">
          <vc_back_b-hed>silencioso   </vc_back_b-hed>
          <vc_back_c-hed>Repita</vc_back_c-hed>
          <vc_back_teacher-talk>Repitan esta palabra: <vc_teacher-talk-emphasis_non-ital>silencioso</vc_teacher-talk-emphasis_non-ital>.</vc_back_teacher-talk>
          <vc_back_c-hed>Defina </vc_back_c-hed>
          <vc_back_teacher-talk>Cuando están silenciosos hacen muy poco ruido.</vc_back_teacher-talk>
          <vc_back_c-hed>Converse </vc_back_c-hed>
          <vc_back_teacher-talk>Esta imagen muestra a una niña que está silenciosa en la biblioteca. ¿En qué otros sitios hay que ser silenciosos?  </vc_back_teacher-talk>
          <vc_teacher-card_body>Repita, reformule o amplíe.</vc_teacher-card_body>
        </section-block>
      </reteach-section>
      <copyright-section>
        <section-block type="copyright_b_6" index="1">
          <vc_back_copyright-line>
            <isbn>978-1-338-66281-8</isbn>. TM ® &amp; © Scholastic Inc. All rights reserved. © Daria Chichkareva/Shutterstock.</vc_back_copyright-line>
        </section-block>
      </copyright-section>
    </vc_card-6_back>
  </vc_card-6>
  <vc_card-7 day="4">
    <vc_card-7_front>
      <graphic href="EC3-5_VC_Eng_Lang_T6W01D4_C1_784406389_cropped.png"/>
      <section-block type="f_7" index="1">
        <vc_front_vocab-word>leopardo</vc_front_vocab-word>
      </section-block>
    </vc_card-7_front>
    <vc_card-7_back>
      <masthead>
        <section-block type="masthead_b_7" index="1">
          <vc_back_component_header>vocabulario</vc_back_component_header>
        </section-block>
      </masthead>
      <introduce-section>
        <section-block type="introduce_b_7" index="1">
          <vc_back_b-hed>leopardo   </vc_back_b-hed>
          <vc_back_c-hed>Repita</vc_back_c-hed>
          <vc_back_teacher-talk>Repitan esta palabra: <vc_teacher-talk-emphasis_non-ital>leopardo</vc_teacher-talk-emphasis_non-ital>.</vc_back_teacher-talk>
          <vc_back_c-hed>Defina </vc_back_c-hed>
          <vc_back_teacher-talk>Un leopardo es un gran gato que tiene manchas. Es un animal salvaje.</vc_back_teacher-talk>
          <vc_back_c-hed>Describa </vc_back_c-hed>
          <vc_back_teacher-talk>Esto es un leopardo. Miren sus manchas negras.</vc_back_teacher-talk>
          <vc_back_c-hed>Represente</vc_back_c-hed>
          <vc_back_teacher-talk>Pongámonos sobre las manos y las rodillas y caminemos por el salón como leopardos.</vc_back_teacher-talk>
        </section-block>
      </introduce-section>
      <reteach-section>
        <section-block type="reteach_b_7" index="1">
          <vc_back_b-hed>leopardo   </vc_back_b-hed>
          <vc_back_c-hed>Repita</vc_back_c-hed>
          <vc_back_teacher-talk>Repitan esta palabra: <vc_teacher-talk-emphasis_non-ital>leopardo</vc_teacher-talk-emphasis_non-ital>.</vc_back_teacher-talk>
          <vc_back_c-hed>Defina </vc_back_c-hed>
          <vc_back_teacher-talk>Un leopardo es un gran gato que tiene manchas. Es un animal salvaje.</vc_back_teacher-talk>
          <vc_back_c-hed>Converse </vc_back_c-hed>
          <vc_back_teacher-talk>Esta imagen muestra un leopardo. ¿Qué observan sobre el leopardo?  </vc_back_teacher-talk>
          <vc_teacher-card_body>Repita, reformule o amplíe.</vc_teacher-card_body>
        </section-block>
      </reteach-section>
      <copyright-section>
        <section-block type="copyright_b_7" index="1">
          <vc_back_copyright-line>
            <isbn>978-1-338-66281-8</isbn>. TM ® &amp; © Scholastic Inc. All rights reserved. © Archna Singh/Shutterstock.</vc_back_copyright-line>
        </section-block>
      </copyright-section>
    </vc_card-7_back>
  </vc_card-7>
  <vc_card-8 day="4">
    <vc_card-8_front>
      <graphic href="EC3-5_VC_Eng_Lang_T6W01D4_C2_712724992_cropped.png"/>
      <section-block type="f_8" index="1">
        <vc_front_vocab-word>rinoceronte</vc_front_vocab-word>
      </section-block>
    </vc_card-8_front>
    <vc_card-8_back>
      <masthead>
        <section-block type="masthead_b_8" index="1">
          <vc_back_component_header>vocabulario</vc_back_component_header>
        </section-block>
      </masthead>
      <introduce-section>
        <section-block type="introduce_b_8" index="1">
          <vc_back_b-hed>rinoceronte   </vc_back_b-hed>
          <vc_back_c-hed>Repita</vc_back_c-hed>
          <vc_back_teacher-talk>Repitan esta palabra: <vc_teacher-talk-emphasis_non-ital>rinoceronte</vc_teacher-talk-emphasis_non-ital>.</vc_back_teacher-talk>
          <vc_back_c-hed>Defina </vc_back_c-hed>
          <vc_back_teacher-talk>Un rinoceronte es un animal grande con piel gruesa y cuernos encima de la nariz.</vc_back_teacher-talk>
          <vc_back_c-hed>Describa </vc_back_c-hed>
          <vc_back_teacher-talk>Esto es un rinoceronte. Miren los cuernos en su nariz.</vc_back_teacher-talk>
          <vc_back_c-hed>Represente</vc_back_c-hed>
          <vc_back_teacher-talk>Muéstrenme cómo creen que se mueven los rinocerontes cuando caminan.      </vc_back_teacher-talk>
        </section-block>
      </introduce-section>
      <reteach-section>
        <section-block type="reteach_b_8" index="1">
          <vc_back_b-hed>rinoceronte   </vc_back_b-hed>
          <vc_back_c-hed>Repita</vc_back_c-hed>
          <vc_back_teacher-talk>Repitan esta palabra: <vc_teacher-talk-emphasis_non-ital>rinoceronte</vc_teacher-talk-emphasis_non-ital>.</vc_back_teacher-talk>
          <vc_back_c-hed>Defina </vc_back_c-hed>
          <vc_back_teacher-talk>Un rinoceronte es un animal grande con piel gruesa y cuernos encima de la nariz.</vc_back_teacher-talk>
          <vc_back_c-hed>Converse </vc_back_c-hed>
          <vc_back_teacher-talk>Esta imagen muestra un rinoceronte. ¿Cómo describirían este rinoceronte? </vc_back_teacher-talk>
          <vc_teacher-card_body>Repita, reformule o amplíe.</vc_teacher-card_body>
        </section-block>
      </reteach-section>
      <copyright-section>
        <section-block type="copyright_b_8" index="1">
          <vc_back_copyright-line>
            <isbn>978-1-338-66281-8</isbn>. TM ® &amp; © Scholastic Inc. All rights reserved. © Volodymyr Burdiak/Shutterstock.</vc_back_copyright-line>
        </section-block>
      </copyright-section>
    </vc_card-8_back>
  </vc_card-8>
  <vc_card-9 day="5">
    <vc_card-9_front>
      <graphic href="EC3-5_VC_Eng_Lang_T6W01D5_C1_486551137_cropped.png"/>
      <section-block type="f_9" index="1">
        <vc_front_vocab-word>motores</vc_front_vocab-word>
      </section-block>
    </vc_card-9_front>
    <vc_card-9_back>
      <masthead>
        <section-block type="masthead_b_9" index="1">
          <vc_back_component_header>vocabulario</vc_back_component_header>
        </section-block>
      </masthead>
      <introduce-section>
        <section-block type="introduce_b_9" index="1">
          <vc_back_b-hed_horiz>motores   </vc_back_b-hed_horiz>
          <vc_back_c-hed>Repita</vc_back_c-hed>
          <vc_back_teacher-talk_horiz>Repitan esta palabra: <vc_teacher-talk-emphasis_non-ital>motores</vc_teacher-talk-emphasis_non-ital>.</vc_back_teacher-talk_horiz>
          <vc_back_c-hed>Defina </vc_back_c-hed>
          <vc_back_teacher-talk_horiz>Los motores son máquinas que hacen un trabajo, como mover un carro. </vc_back_teacher-talk_horiz>
          <vc_back_c-hed>Describa </vc_back_c-hed>
          <vc_back_teacher-talk_horiz>Este carro tiene un motor. El motor hace que el carro se mueva.</vc_back_teacher-talk_horiz>
          <vc_back_c-hed>Represente</vc_back_c-hed>
          <vc_back_teacher-talk_horiz>Los motores hacen un ruido como brrrum, brrrum, brrrum. Hagan este sonido conmigo: brrrum, brrrum, brrrum. </vc_back_teacher-talk_horiz>
        </section-block>
      </introduce-section>
      <reteach-section>
        <section-block type="reteach_b_9" index="1">
          <vc_back_b-hed_horiz>motores   </vc_back_b-hed_horiz>
          <vc_back_c-hed>Repita</vc_back_c-hed>
          <vc_back_teacher-talk_horiz>Repitan esta palabra: <vc_teacher-talk-emphasis_non-ital>motores</vc_teacher-talk-emphasis_non-ital>.</vc_back_teacher-talk_horiz>
          <vc_back_c-hed>Defina </vc_back_c-hed>
          <vc_back_teacher-talk_horiz>Los motores son máquinas que hacen un trabajo, como mover un carro. </vc_back_teacher-talk_horiz>
          <vc_back_c-hed>Converse </vc_back_c-hed>
          <vc_back_teacher-talk_horiz>Esta imagen muestra el motor de un carro. ¿Qué otras cosas creen que tienen motor? </vc_back_teacher-talk_horiz>
          <vc_teacher-card_body>Repita, reformule o amplíe.</vc_teacher-card_body>
        </section-block>
      </reteach-section>
      <copyright-section>
        <section-block type="copyright_b_9" index="1">
          <vc_back_copyright-line>
            <isbn>978-1-338-66281-8</isbn>. TM ® &amp; © Scholastic Inc. All rights reserved. © NosorogUA/Shutterstock.</vc_back_copyright-line>
        </section-block>
      </copyright-section>
    </vc_card-9_back>
  </vc_card-9>
  <vc_card-10 day="5">
    <vc_card-10_front>
      <graphic href="EC3-5_VC_Eng_Lang_T6W01D5_C2_1397658245_cropped.png"/>
      <section-block type="f_10" index="1">
        <vc_front_vocab-word>alegre</vc_front_vocab-word>
      </section-block>
    </vc_card-10_front>
    <vc_card-10_back>
      <masthead>
        <section-block type="masthead_b_10" index="1">
          <vc_back_component_header>vocabulario</vc_back_component_header>
        </section-block>
      </masthead>
      <introduce-section>
        <section-block type="introduce_b_10" index="1">
          <vc_back_b-hed_horiz>alegre   </vc_back_b-hed_horiz>
          <vc_back_c-hed>Repita</vc_back_c-hed>
          <vc_back_teacher-talk_horiz>Repitan esta palabra: <vc_teacher-talk-emphasis_non-ital>alegre</vc_teacher-talk-emphasis_non-ital>.</vc_back_teacher-talk_horiz>
          <vc_back_c-hed>Defina </vc_back_c-hed>
          <vc_back_teacher-talk_horiz>Cuando alguien está alegre, está feliz.</vc_back_teacher-talk_horiz>
          <vc_back_c-hed>Describa </vc_back_c-hed>
          <vc_back_teacher-talk_horiz>El niño de la imagen está alegre. ¿Qué observan en su cara?</vc_back_teacher-talk_horiz>
          <vc_back_c-hed>Represente</vc_back_c-hed>
          <vc_back_teacher-talk_horiz>Imaginen que están alegres. Muéstrenme sus caras alegres.</vc_back_teacher-talk_horiz>
        </section-block>
      </introduce-section>
      <reteach-section>
        <section-block type="reteach_b_10" index="1">
          <vc_back_b-hed_horiz>alegre   </vc_back_b-hed_horiz>
          <vc_back_c-hed>Repita</vc_back_c-hed>
          <vc_back_teacher-talk_horiz>Repitan esta palabra: <vc_teacher-talk-emphasis_non-ital>alegre</vc_teacher-talk-emphasis_non-ital>.</vc_back_teacher-talk_horiz>
          <vc_back_c-hed>Defina </vc_back_c-hed>
          <vc_back_teacher-talk_horiz>Cuando alguien está alegre, está feliz.</vc_back_teacher-talk_horiz>
          <vc_back_c-hed>Converse </vc_back_c-hed>
          <vc_back_teacher-talk_horiz>Miren la imagen. ¿Por qué creen que está alegre el niño? </vc_back_teacher-talk_horiz>
          <vc_teacher-card_body>Repita, reformule o amplíe.</vc_teacher-card_body>
        </section-block>
      </reteach-section>
      <copyright-section>
        <section-block type="copyright_b_10" index="1">
          <vc_back_copyright-line>
            <isbn>978-1-338-66281-8</isbn>. TM ® &amp; © Scholastic Inc. All rights reserved. © AnnGaysorn/Shutterstock.</vc_back_copyright-line>
        </section-block>
      </copyright-section>
    </vc_card-10_back>
  </vc_card-10>
</vocabulary-card>
