<?xml version="1.0" encoding="UTF-8"?>
<vocabulary-card lang="es">
  <vc_card-1 day="1">
    <vc_card-1_front>
      <graphic href="EC3-5_VC_Eng_Math_T7W02D1_C1_212520601_cropped.png"/>
      <section-block type="f_1" index="1">
        <vc_front_vocab-word>primavera</vc_front_vocab-word>
      </section-block>
    </vc_card-1_front>
    <vc_card-1_back>
      <masthead>
        <section-block type="masthead_b_1" index="1">
          <vc_back_component_header>vocabulario</vc_back_component_header>
        </section-block>
      </masthead>
      <introduce-section>
        <section-block type="introduce_b_1" index="1">
          <vc_back_b-hed>primavera   </vc_back_b-hed>
          <vc_back_c-hed>Repita</vc_back_c-hed>
          <vc_back_teacher-talk>Repitan esta palabra: <vc_teacher-talk-emphasis_non-ital>primavera</vc_teacher-talk-emphasis_non-ital>.</vc_back_teacher-talk>
          <vc_back_c-hed>Defina</vc_back_c-hed>
          <vc_back_teacher-talk>La primavera es la estación entre el invierno y el verano. En muchos lugares, en primavera el clima es algo cálido.</vc_back_teacher-talk>
          <vc_back_c-hed>Describa</vc_back_c-hed>
          <vc_back_teacher-talk>En primavera, las flores y los árboles vuelven a crecer.</vc_back_teacher-talk>
          <vc_back_c-hed>Represente</vc_back_c-hed>
          <vc_back_teacher-talk>Simulemos que estamos oliendo flores en primavera. Mmmm. ¡Huelen tan bien!</vc_back_teacher-talk>
        </section-block>
      </introduce-section>
      <reteach-section>
        <section-block type="reteach_b_1" index="1">
          <vc_back_b-hed>primavera   </vc_back_b-hed>
          <vc_back_c-hed>Repita</vc_back_c-hed>
          <vc_back_teacher-talk>Repitan esta palabra: <vc_teacher-talk-emphasis_non-ital>primavera</vc_teacher-talk-emphasis_non-ital>.</vc_back_teacher-talk>
          <vc_back_c-hed>Defina</vc_back_c-hed>
          <vc_back_teacher-talk>La primavera es la estación entre el invierno y el verano. En muchos lugares, en primavera el clima es algo cálido.</vc_back_teacher-talk>
          <vc_back_c-hed>Converse</vc_back_c-hed>
          <vc_back_teacher-talk>Miren la imagen de las flores que crecen en el árbol. ¿Qué les gusta hacer en primavera?</vc_back_teacher-talk>
          <vc_teacher-card_body>Repita, reformule o amplíe.</vc_teacher-card_body>
        </section-block>
      </reteach-section>
      <copyright-section>
        <section-block type="copyright_b_1" index="1">
          <vc_back_copyright-line>
            <isbn>978-1-338-66380-8</isbn>. TM ® &amp; © Scholastic Inc. All rights reserved. © Pawel Kazmierczak/Shutterstock.</vc_back_copyright-line>
        </section-block>
      </copyright-section>
    </vc_card-1_back>
  </vc_card-1>
  <vc_card-2 day="1">
    <vc_card-2_front>
      <graphic href="EC3-5_VC_Eng_Math_T7W02D1_C2_1478576471_cropped.png"/>
      <section-block type="f_2" index="1">
        <vc_front_vocab-word>otoño</vc_front_vocab-word>
      </section-block>
    </vc_card-2_front>
    <vc_card-2_back>
      <masthead>
        <section-block type="masthead_b_2" index="1">
          <vc_back_component_header>vocabulario</vc_back_component_header>
        </section-block>
      </masthead>
      <introduce-section>
        <section-block type="introduce_b_2" index="1">
          <vc_back_b-hed>otoño   </vc_back_b-hed>
          <vc_back_c-hed>Repita</vc_back_c-hed>
          <vc_back_teacher-talk>Repitan esta palabra: <vc_teacher-talk-emphasis_non-ital>otoño</vc_teacher-talk-emphasis_non-ital>.</vc_back_teacher-talk>
          <vc_back_c-hed>Defina</vc_back_c-hed>
          <vc_back_teacher-talk>El otoño es la estación entre el verano y el invierno. En muchos lugares, en otoño el clima se vuelve más fresco.</vc_back_teacher-talk>
          <vc_back_c-hed>Describa</vc_back_c-hed>
          <vc_back_teacher-talk>En otoño, las hojas cambian de color y se caen de los árboles.</vc_back_teacher-talk>
          <vc_back_c-hed>Represente</vc_back_c-hed>
          <vc_back_teacher-talk>Simulemos que saltamos sobre un montón de hojas. ¡Yupiii! </vc_back_teacher-talk>
        </section-block>
      </introduce-section>
      <reteach-section>
        <section-block type="reteach_b_2" index="1">
          <vc_back_b-hed>otoño   </vc_back_b-hed>
          <vc_back_c-hed>Repita</vc_back_c-hed>
          <vc_back_teacher-talk>Repitan esta palabra: <vc_teacher-talk-emphasis_non-ital>otoño</vc_teacher-talk-emphasis_non-ital>.</vc_back_teacher-talk>
          <vc_back_c-hed>Defina</vc_back_c-hed>
          <vc_back_teacher-talk>El otoño es la estación entre el verano y el invierno. En muchos lugares, en otoño el clima se vuelve más fresco.</vc_back_teacher-talk>
          <vc_back_c-hed>Converse</vc_back_c-hed>
          <vc_back_teacher-talk>Miren la imagen de estas hojas coloridas de otoño. ¿Qué les gusta hacer en otoño?</vc_back_teacher-talk>
          <vc_teacher-card_body>Repita, reformule o amplíe.</vc_teacher-card_body>
        </section-block>
      </reteach-section>
      <copyright-section>
        <section-block type="copyright_b_2" index="1">
          <vc_back_copyright-line>
            <isbn>978-1-338-66380-8</isbn>. TM ® &amp; © Scholastic Inc. All rights reserved. © LutsenkoLarissa/Shutterstock.</vc_back_copyright-line>
        </section-block>
      </copyright-section>
    </vc_card-2_back>
  </vc_card-2>
  <vc_card-3 day="2">
    <vc_card-3_front>
      <graphic href="EC3-5_VC_Eng_Math_T7W02D2_C1_1245120310_cropped.png"/>
      <section-block type="f_3" index="1">
        <vc_front_vocab-word>imaginar</vc_front_vocab-word>
      </section-block>
    </vc_card-3_front>
    <vc_card-3_back>
      <masthead>
        <section-block type="masthead_b_3" index="1">
          <vc_back_component_header>vocabulario</vc_back_component_header>
        </section-block>
      </masthead>
      <introduce-section>
        <section-block type="introduce_b_3" index="1">
          <vc_back_b-hed>imaginar   </vc_back_b-hed>
          <vc_back_c-hed>Repita</vc_back_c-hed>
          <vc_back_teacher-talk>Repitan esta palabra: <vc_teacher-talk-emphasis_non-ital>imaginar</vc_teacher-talk-emphasis_non-ital>.</vc_back_teacher-talk>
          <vc_back_c-hed>Defina</vc_back_c-hed>
          <vc_back_teacher-talk>Cuando imaginan, pueden crear una imagen en la mente.</vc_back_teacher-talk>
          <vc_back_c-hed>Describa</vc_back_c-hed>
          <vc_back_teacher-talk>Cuando imaginan algo, piensan en cómo se vería o cómo sería si fuera real.</vc_back_teacher-talk>
          <vc_back_c-hed>Represente</vc_back_c-hed>
          <vc_back_teacher-talk>Imaginen que son un perro. ¿Cómo actuarían?  </vc_back_teacher-talk>
        </section-block>
      </introduce-section>
      <reteach-section>
        <section-block type="reteach_b_3" index="1">
          <vc_back_b-hed>imaginar   </vc_back_b-hed>
          <vc_back_c-hed>Repita</vc_back_c-hed>
          <vc_back_teacher-talk>Repitan esta palabra: <vc_teacher-talk-emphasis_non-ital>imaginar</vc_teacher-talk-emphasis_non-ital>.</vc_back_teacher-talk>
          <vc_back_c-hed>Defina</vc_back_c-hed>
          <vc_back_teacher-talk>Cuando imaginan, pueden crear una imagen en la mente.</vc_back_teacher-talk>
          <vc_back_c-hed>Converse</vc_back_c-hed>
          <vc_back_teacher-talk>Miren la imagen de un niño imaginando algo. ¿Qué creen que está imaginando?</vc_back_teacher-talk>
          <vc_teacher-card_body>Repita, reformule o amplíe.</vc_teacher-card_body>
        </section-block>
      </reteach-section>
      <copyright-section>
        <section-block type="copyright_b_3" index="1">
          <vc_back_copyright-line>
            <isbn>978-1-338-66380-8</isbn>. TM ® &amp; © Scholastic Inc. All rights reserved. © Gelpi/Shutterstock.</vc_back_copyright-line>
        </section-block>
      </copyright-section>
    </vc_card-3_back>
  </vc_card-3>
  <vc_card-4 day="3">
    <vc_card-4_front>
      <graphic href="EC3-5_VC_Eng_Math_T7W02D3_C1_1452550547_cropped.png"/>
      <section-block type="f_4" index="1">
        <vc_front_vocab-word>arriba</vc_front_vocab-word>
      </section-block>
    </vc_card-4_front>
    <vc_card-4_back>
      <masthead>
        <section-block type="masthead_b_4" index="1">
          <vc_back_component_header>vocabulario</vc_back_component_header>
        </section-block>
      </masthead>
      <introduce-section>
        <section-block type="introduce_b_4" index="1">
          <vc_back_b-hed>arriba   </vc_back_b-hed>
          <vc_back_c-hed>Repita</vc_back_c-hed>
          <vc_back_teacher-talk>Repitan esta palabra: <vc_teacher-talk-emphasis_non-ital>arriba</vc_teacher-talk-emphasis_non-ital>.</vc_back_teacher-talk>
          <vc_back_c-hed>Defina</vc_back_c-hed>
          <vc_back_teacher-talk>Arriba es la parte más alta de algo.</vc_back_teacher-talk>
          <vc_back_c-hed>Describa</vc_back_c-hed>
          <vc_back_teacher-talk>La parte de arriba de un árbol tiene hojas.</vc_back_teacher-talk>
          <vc_back_c-hed>Represente</vc_back_c-hed>
          <vc_back_teacher-talk>Señalen la parte de arriba de su cabeza. Señalen la parte de arriba de la puerta.   </vc_back_teacher-talk>
        </section-block>
      </introduce-section>
      <reteach-section>
        <section-block type="reteach_b_4" index="1">
          <vc_back_b-hed>arriba   </vc_back_b-hed>
          <vc_back_c-hed>Repita</vc_back_c-hed>
          <vc_back_teacher-talk>Repitan esta palabra: <vc_teacher-talk-emphasis_non-ital>arriba</vc_teacher-talk-emphasis_non-ital>.</vc_back_teacher-talk>
          <vc_back_c-hed>Defina</vc_back_c-hed>
          <vc_back_teacher-talk>Arriba es la parte más alta de algo.</vc_back_teacher-talk>
          <vc_back_c-hed>Converse</vc_back_c-hed>
          <vc_back_teacher-talk>Miren la imagen de la parte de arriba de un árbol. ¿Qué creen que hay ahí arriba?</vc_back_teacher-talk>
          <vc_teacher-card_body>Repita, reformule o amplíe.</vc_teacher-card_body>
        </section-block>
      </reteach-section>
      <copyright-section>
        <section-block type="copyright_b_4" index="1">
          <vc_back_copyright-line>
            <isbn>978-1-338-66380-8</isbn>. TM ® &amp; © Scholastic Inc. All rights reserved. © Richie Bednarski/Shutterstock.</vc_back_copyright-line>
        </section-block>
      </copyright-section>
    </vc_card-4_back>
  </vc_card-4>
  <vc_card-5 day="3">
    <vc_card-5_front>
      <graphic href="EC3-5_VC_Eng_Math_T7W02D3_C2_101096695_cropped.png"/>
      <section-block type="f_5" index="1">
        <vc_front_vocab-word>abajo</vc_front_vocab-word>
      </section-block>
    </vc_card-5_front>
    <vc_card-5_back>
      <masthead>
        <section-block type="masthead_b_5" index="1">
          <vc_back_component_header>vocabulario</vc_back_component_header>
        </section-block>
      </masthead>
      <introduce-section>
        <section-block type="introduce_b_5" index="1">
          <vc_back_b-hed>abajo   </vc_back_b-hed>
          <vc_back_c-hed>Repita</vc_back_c-hed>
          <vc_back_teacher-talk>Repitan esta palabra: <vc_teacher-talk-emphasis_non-ital>abajo</vc_teacher-talk-emphasis_non-ital>.</vc_back_teacher-talk>
          <vc_back_c-hed>Defina</vc_back_c-hed>
          <vc_back_teacher-talk>Abajo es la parte más baja de algo.</vc_back_teacher-talk>
          <vc_back_c-hed>Describa</vc_back_c-hed>
          <vc_back_teacher-talk>La parte de abajo de un árbol crece en la tierra.</vc_back_teacher-talk>
          <vc_back_c-hed>Represente</vc_back_c-hed>
          <vc_back_teacher-talk>Señalen la parte de abajo de los pies. Señalen la parte de abajo de la pared.  </vc_back_teacher-talk>
        </section-block>
      </introduce-section>
      <reteach-section>
        <section-block type="reteach_b_5" index="1">
          <vc_back_b-hed>abajo   </vc_back_b-hed>
          <vc_back_c-hed>Repita</vc_back_c-hed>
          <vc_back_teacher-talk>Repitan esta palabra: <vc_teacher-talk-emphasis_non-ital>abajo</vc_teacher-talk-emphasis_non-ital>.</vc_back_teacher-talk>
          <vc_back_c-hed>Defina</vc_back_c-hed>
          <vc_back_teacher-talk>Abajo es la parte más baja de algo.</vc_back_teacher-talk>
          <vc_back_c-hed>Converse</vc_back_c-hed>
          <vc_back_teacher-talk>Miren la imagen de la parte de abajo de un árbol. ¿Qué creen que hay ahí abajo?</vc_back_teacher-talk>
          <vc_teacher-card_body>Repita, reformule o amplíe.</vc_teacher-card_body>
        </section-block>
      </reteach-section>
      <copyright-section>
        <section-block type="copyright_b_5" index="1">
          <vc_back_copyright-line>
            <isbn>978-1-338-66380-8</isbn>. TM ® &amp; © Scholastic Inc. All rights reserved. © Andreiuc88/Shutterstock.</vc_back_copyright-line>
        </section-block>
      </copyright-section>
    </vc_card-5_back>
  </vc_card-5>
  <vc_card-6 day="4">
    <vc_card-6_front>
      <graphic href="EC3-5_VC_Spa_Math_T7W02D4_C1_693450487_cropped.png"/>
      <section-block type="f_6" index="1">
        <vc_front_vocab-word>plantamos</vc_front_vocab-word>
      </section-block>
    </vc_card-6_front>
    <vc_card-6_back>
      <masthead>
        <section-block type="masthead_b_6" index="1">
          <vc_back_component_header>vocabulario</vc_back_component_header>
        </section-block>
      </masthead>
      <introduce-section>
        <section-block type="introduce_b_6" index="1">
          <vc_back_b-hed>plantamos   </vc_back_b-hed>
          <vc_back_c-hed>Repita</vc_back_c-hed>
          <vc_back_teacher-talk>Repitan esta palabra: <vc_teacher-talk-emphasis_non-ital>plantamos</vc_teacher-talk-emphasis_non-ital>.</vc_back_teacher-talk>
          <vc_back_c-hed>Defina</vc_back_c-hed>
          <vc_back_teacher-talk>Cuando plantamos, ponemos una semilla en la tierra para que crezca una planta.</vc_back_teacher-talk>
          <vc_back_c-hed>Describa</vc_back_c-hed>
          <vc_back_teacher-talk>Podemos plantar flores en la tierra.</vc_back_teacher-talk>
          <vc_back_c-hed>Represente</vc_back_c-hed>
          <vc_back_teacher-talk>Simulen que plantan algo en el jardín. Hagan un hoyo y pongan la semilla dentro. Ahora cúbranla de tierra.   </vc_back_teacher-talk>
        </section-block>
      </introduce-section>
      <reteach-section>
        <section-block type="reteach_b_6" index="1">
          <vc_back_b-hed>plantamos   </vc_back_b-hed>
          <vc_back_c-hed>Repita</vc_back_c-hed>
          <vc_back_teacher-talk>Repitan esta palabra: <vc_teacher-talk-emphasis_non-ital>plantamos</vc_teacher-talk-emphasis_non-ital>.</vc_back_teacher-talk>
          <vc_back_c-hed>Defina</vc_back_c-hed>
          <vc_back_teacher-talk>Cuando plantamos, ponemos una semilla en la tierra para que crezca una planta.</vc_back_teacher-talk>
          <vc_back_c-hed>Converse</vc_back_c-hed>
          <vc_back_teacher-talk>Miren esta imagen de un niño plantando cosas en un jardín. ¿Qué les gustaría plantar a ustedes?</vc_back_teacher-talk>
          <vc_teacher-card_body>Repita, reformule o amplíe.</vc_teacher-card_body>
        </section-block>
      </reteach-section>
      <copyright-section>
        <section-block type="copyright_b_6" index="1">
          <vc_back_copyright-line>
            <isbn>978-1-338-66380-8</isbn>. TM ® &amp; © Scholastic Inc. All rights reserved. © ANURAK PONGPATIMET/Shutterstock.</vc_back_copyright-line>
        </section-block>
      </copyright-section>
    </vc_card-6_back>
  </vc_card-6>
  <vc_card-7 day="4">
    <vc_card-7_front>
      <graphic href="EC3-5_VC_Eng_Math_T7W02D4_C2_77123302_cropped.png"/>
      <section-block type="f_7" index="1">
        <vc_front_vocab-word>estaciones</vc_front_vocab-word>
      </section-block>
    </vc_card-7_front>
    <vc_card-7_back>
      <masthead>
        <section-block type="masthead_b_7" index="1">
          <vc_back_component_header>VocabularIO</vc_back_component_header>
        </section-block>
      </masthead>
      <introduce-section>
        <section-block type="introduce_b_7" index="1">
          <vc_back_b-hed_horiz>estaciones   </vc_back_b-hed_horiz>
          <vc_back_c-hed>Repita</vc_back_c-hed>
          <vc_back_teacher-talk_horiz>Repitan esta palabra: <vc_teacher-talk-emphasis_non-ital>estaciones</vc_teacher-talk-emphasis_non-ital>.</vc_back_teacher-talk_horiz>
          <vc_back_c-hed>Defina</vc_back_c-hed>
          <vc_back_teacher-talk_horiz>Hay cuatro estaciones en el año: primavera, verano, otoño e invierno.</vc_back_teacher-talk_horiz>
          <vc_back_c-hed>Describa</vc_back_c-hed>
          <vc_back_teacher-talk_horiz>Las hojas de muchos árboles cambian según la estación.</vc_back_teacher-talk_horiz>
          <vc_back_c-hed>Represente</vc_back_c-hed>
          <vc_back_teacher-talk_horiz>Hay cuatro estaciones en el año. Simulemos que es invierno. ¡Brrrr! Ahora simulemos que es verano. ¡Uf! ¡Qué calor! Simulen que hacen lo que les gusta hacer afuera en esa estación.</vc_back_teacher-talk_horiz>
        </section-block>
      </introduce-section>
      <reteach-section>
        <section-block type="reteach_b_7" index="1">
          <vc_back_b-hed_horiz>estaciones   </vc_back_b-hed_horiz>
          <vc_back_c-hed>Repita</vc_back_c-hed>
          <vc_back_teacher-talk_horiz>Repitan esta palabra: <vc_teacher-talk-emphasis_non-ital>estaciones</vc_teacher-talk-emphasis_non-ital>.</vc_back_teacher-talk_horiz>
          <vc_back_c-hed>Defina</vc_back_c-hed>
          <vc_back_teacher-talk_horiz>Hay cuatro estaciones en el año: primavera, verano, otoño e invierno.</vc_back_teacher-talk_horiz>
          <vc_back_c-hed>Converse</vc_back_c-hed>
          <vc_back_teacher-talk_horiz>Miren imágenes de las cuatro estaciones. ¿Qué estaciones les gustan? ¿Por qué?</vc_back_teacher-talk_horiz>
          <vc_teacher-card_body>Repita, reformule o amplíe.</vc_teacher-card_body>
        </section-block>
      </reteach-section>
      <copyright-section>
        <section-block type="copyright_b_7" index="1">
          <vc_back_copyright-line>
            <isbn>978-1-338-66380-8</isbn>. TM ® &amp; © Scholastic Inc. All rights reserved. © Ingrid Prats/Shutterstock.</vc_back_copyright-line>
        </section-block>
      </copyright-section>
    </vc_card-7_back>
  </vc_card-7>
  <vc_card-8 day="5">
    <vc_card-8_front>
      <graphic href="EC3-5_VC_Eng_Math_T7W02D5_C1_51413575_cropped.png"/>
      <section-block type="f_8" index="1">
        <vc_front_vocab-word>verano</vc_front_vocab-word>
      </section-block>
    </vc_card-8_front>
    <vc_card-8_back>
      <masthead>
        <section-block type="masthead_b_8" index="1">
          <vc_back_component_header>vocabulario</vc_back_component_header>
        </section-block>
      </masthead>
      <introduce-section>
        <section-block type="introduce_b_8" index="1">
          <vc_back_b-hed>verano   </vc_back_b-hed>
          <vc_back_c-hed>Repita</vc_back_c-hed>
          <vc_back_teacher-talk>Repitan esta palabra: <vc_teacher-talk-emphasis_non-ital>verano</vc_teacher-talk-emphasis_non-ital>.</vc_back_teacher-talk>
          <vc_back_c-hed>Defina</vc_back_c-hed>
          <vc_back_teacher-talk>El verano es la estación entre la primavera y el otoño. En muchos lugares, el clima es muy caluroso en verano.</vc_back_teacher-talk>
          <vc_back_c-hed>Describa</vc_back_c-hed>
          <vc_back_teacher-talk>En verano, a algunas personas les gusta estar en el agua o cerca de ella.</vc_back_teacher-talk>
          <vc_back_c-hed>Represente</vc_back_c-hed>
          <vc_back_teacher-talk>Simulemos que nadan en un día caluroso de verano. </vc_back_teacher-talk>
        </section-block>
      </introduce-section>
      <reteach-section>
        <section-block type="reteach_b_8" index="1">
          <vc_back_b-hed>verano   </vc_back_b-hed>
          <vc_back_c-hed>Repita</vc_back_c-hed>
          <vc_back_teacher-talk>Repitan esta palabra: <vc_teacher-talk-emphasis_non-ital>verano</vc_teacher-talk-emphasis_non-ital>.</vc_back_teacher-talk>
          <vc_back_c-hed>Defina</vc_back_c-hed>
          <vc_back_teacher-talk>El verano es la estación entre la primavera y el otoño. En muchos lugares, el clima es muy caluroso en verano.</vc_back_teacher-talk>
          <vc_back_c-hed>Converse</vc_back_c-hed>
          <vc_back_teacher-talk>Miren la imagen de una playa en verano. ¿Qué les gusta hacer en verano?</vc_back_teacher-talk>
          <vc_teacher-card_body>Repita, reformule o amplíe.</vc_teacher-card_body>
        </section-block>
      </reteach-section>
      <copyright-section>
        <section-block type="copyright_b_8" index="1">
          <vc_back_copyright-line>
            <isbn>978-1-338-66380-8</isbn>. TM ® &amp; © Scholastic Inc. All rights reserved. © leoks/Shutterstock.</vc_back_copyright-line>
        </section-block>
      </copyright-section>
    </vc_card-8_back>
  </vc_card-8>
  <vc_card-9 day="5">
    <vc_card-9_front>
      <graphic href="EC3-5_VC_Eng_Math_T7W02D5_C2_69973288_cropped.png"/>
      <section-block type="f_9" index="1">
        <vc_front_vocab-word>invierno</vc_front_vocab-word>
      </section-block>
    </vc_card-9_front>
    <vc_card-9_back>
      <masthead>
        <section-block type="masthead_b_9" index="1">
          <vc_back_component_header>vocabulario</vc_back_component_header>
        </section-block>
      </masthead>
      <introduce-section>
        <section-block type="introduce_b_9" index="1">
          <vc_back_b-hed>invierno   </vc_back_b-hed>
          <vc_back_c-hed>Repita</vc_back_c-hed>
          <vc_back_teacher-talk>Repitan esta palabra: <vc_teacher-talk-emphasis_non-ital>invierno</vc_teacher-talk-emphasis_non-ital>.</vc_back_teacher-talk>
          <vc_back_c-hed>Defina</vc_back_c-hed>
          <vc_back_teacher-talk>El invierno es la estación entre el otoño y la primavera. En muchos lugares, el clima es frío en invierno.</vc_back_teacher-talk>
          <vc_back_c-hed>Describa</vc_back_c-hed>
          <vc_back_teacher-talk>A veces nieva en invierno.</vc_back_teacher-talk>
          <vc_back_c-hed>Represente</vc_back_c-hed>
          <vc_back_teacher-talk>Simulen que juegan en la nieve. ¡Pónganse los guantes y los gorros antes de jugar en la nieve! </vc_back_teacher-talk>
        </section-block>
      </introduce-section>
      <reteach-section>
        <section-block type="reteach_b_9" index="1">
          <vc_back_b-hed>invierno   </vc_back_b-hed>
          <vc_back_c-hed>Repita</vc_back_c-hed>
          <vc_back_teacher-talk>Repitan esta palabra: <vc_teacher-talk-emphasis_non-ital>invierno</vc_teacher-talk-emphasis_non-ital>.</vc_back_teacher-talk>
          <vc_back_c-hed>Defina</vc_back_c-hed>
          <vc_back_teacher-talk>El invierno es la estación entre el otoño y la primavera. En muchos lugares, el clima es frío en invierno.</vc_back_teacher-talk>
          <vc_back_c-hed>Converse</vc_back_c-hed>
          <vc_back_teacher-talk>Miren la imagen de la nieve. ¿Qué les gusta hacer en invierno?</vc_back_teacher-talk>
          <vc_teacher-card_body>Repita, reformule o amplíe.</vc_teacher-card_body>
        </section-block>
      </reteach-section>
      <copyright-section>
        <section-block type="copyright_b_9" index="1">
          <vc_back_copyright-line>
            <isbn>978-1-338-66380-8</isbn>. TM ® &amp; © Scholastic Inc. All rights reserved. © Jevgenijsdasko/Shutterstock.</vc_back_copyright-line>
        </section-block>
      </copyright-section>
    </vc_card-9_back>
  </vc_card-9>
</vocabulary-card>
