<?xml version="1.0" encoding="UTF-8"?>
<activity-cards lang="en">
  <ac_card-1 day="3">
    <ac_card-1_front>
      <graphic href="EC3-5_AC_Eng_Lang_T3W02D3_C1_01_159902465_cropped.png"/>
    </ac_card-1_front>
    <ac_card-1_back>
      <masthead>
        <section-block type="masthead_b_1" index="1">
          <ac_header-game-card>WHAT DO CLOUDS MAKE? </ac_header-game-card>
        </section-block>
      </masthead>
      <ask-section>
        <section-block type="ask_b_1" index="1">
          <ac_ask-extend-hed>Ask</ac_ask-extend-hed>
          <ac_game_card-teacher-talk-white>Is this a picture of stormy weather or calm weather?</ac_game_card-teacher-talk-white>
        </section-block>
      </ask-section>
      <support-section>
        <section-block type="support_b_1" index="1">
          <ac_support-challenge-hed>Support</ac_support-challenge-hed>
          <ac_game_card-teacher-talk-solid>This is a picture of st<fill-in-the-blank>            </fill-in-the-blank> <ac_teacher-talk-emphasis_non-ital>(stormy)</ac_teacher-talk-emphasis_non-ital> weather.  </ac_game_card-teacher-talk-solid>
        </section-block>
      </support-section>
      <challenge-section>
        <section-block type="challenge_b_1" index="1">
          <ac_support-challenge-hed>Challenge</ac_support-challenge-hed>
          <ac_game_card-teacher-talk-solid>Look at the clouds in this picture. Describe what you see.</ac_game_card-teacher-talk-solid>
        </section-block>
      </challenge-section>
      <extend-section>
        <section-block type="extend_b_1" index="1">
          <ac_ask-extend-hed>Extend</ac_ask-extend-hed>
          <ac_game_card-teacher-talk-white>Have you ever seen clouds like these? What weather did they bring? What did you do?</ac_game_card-teacher-talk-white>
        </section-block>
      </extend-section>
      <copyright-section>
        <section-block type="copyright_b_1" index="1">
          <ac_copyright-line>
            <isbn>978-1-338-65167-6</isbn>. TM ® &amp; © Scholastic Inc. All rights reserved. © Gwoeii/Shutterstock.</ac_copyright-line>
        </section-block>
      </copyright-section>
    </ac_card-1_back>
  </ac_card-1>
  <ac_card-2 day="3">
    <ac_card-2_front>
      <graphic href="EC3-5_AC_Eng_Lang_T3W02D3_C2_01_782823046_cropped.png"/>
    </ac_card-2_front>
    <ac_card-2_back>
      <masthead>
        <section-block type="masthead_b_2" index="1">
          <ac_header-game-card>WHAT DO CLOUDS MAKE? </ac_header-game-card>
        </section-block>
      </masthead>
      <ask-section>
        <section-block type="ask_b_2" index="1">
          <ac_ask-extend-hed>Ask</ac_ask-extend-hed>
          <ac_game_card-teacher-talk-white>Is this a picture of rainy weather or sunny weather?</ac_game_card-teacher-talk-white>
        </section-block>
      </ask-section>
      <support-section>
        <section-block type="support_b_2" index="1">
          <ac_support-challenge-hed>Support</ac_support-challenge-hed>
          <ac_game_card-teacher-talk-solid>This is a picture of r<fill-in-the-blank>            </fill-in-the-blank> <ac_teacher-talk-emphasis_non-ital>(rainy)</ac_teacher-talk-emphasis_non-ital> weather.</ac_game_card-teacher-talk-solid>
        </section-block>
      </support-section>
      <challenge-section>
        <section-block type="challenge_b_2" index="1">
          <ac_support-challenge-hed>Challenge</ac_support-challenge-hed>
          <ac_game_card-teacher-talk-solid>What does rain feel like? Do you think this is a cold rain or a warm rain? Why?</ac_game_card-teacher-talk-solid>
        </section-block>
      </challenge-section>
      <extend-section>
        <section-block type="extend_b_2" index="1">
          <ac_ask-extend-hed>Extend</ac_ask-extend-hed>
          <ac_game_card-teacher-talk-white>Have you seen rain like this? Was it heavy rain or light rain? What did you do?</ac_game_card-teacher-talk-white>
        </section-block>
      </extend-section>
      <copyright-section>
        <section-block type="copyright_b_2" index="1">
          <ac_copyright-line>
            <isbn>978-1-338-65167-6</isbn>. TM ® &amp; © Scholastic Inc. All rights reserved. © Mumemories/Shutterstock.</ac_copyright-line>
        </section-block>
      </copyright-section>
    </ac_card-2_back>
  </ac_card-2>
  <ac_card-3 day="3">
    <ac_card-3_front>
      <graphic href="EC3-5_AC_Eng_Lang_T3W02D3_C3_01_65255689_cropped.png"/>
    </ac_card-3_front>
    <ac_card-3_back>
      <masthead>
        <section-block type="masthead_b_3" index="1">
          <ac_header-game-card>WHAT DO CLOUDS MAKE? </ac_header-game-card>
        </section-block>
      </masthead>
      <ask-section>
        <section-block type="ask_b_3" index="1">
          <ac_ask-extend-hed>Ask</ac_ask-extend-hed>
          <ac_game_card-teacher-talk-white>Is this a picture of rain or of snow?</ac_game_card-teacher-talk-white>
        </section-block>
      </ask-section>
      <support-section>
        <section-block type="support_b_3" index="1">
          <ac_support-challenge-hed>Support</ac_support-challenge-hed>
          <ac_game_card-teacher-talk-solid>This is a picture of sn<fill-in-the-blank>         </fill-in-the-blank> <ac_teacher-talk-emphasis_non-ital>(snow)</ac_teacher-talk-emphasis_non-ital>.</ac_game_card-teacher-talk-solid>
        </section-block>
      </support-section>
      <challenge-section>
        <section-block type="challenge_b_3" index="1">
          <ac_support-challenge-hed>Challenge</ac_support-challenge-hed>
          <ac_game_card-teacher-talk-solid>What does snow feel like? What do people like to do when it snows?</ac_game_card-teacher-talk-solid>
        </section-block>
      </challenge-section>
      <extend-section>
        <section-block type="extend_b_3" index="1">
          <ac_ask-extend-hed>Extend</ac_ask-extend-hed>
          <ac_game_card-teacher-talk-white>Have you ever seen snow falling from clouds? Was it heavy snow or light snow? Tell about it.</ac_game_card-teacher-talk-white>
        </section-block>
      </extend-section>
      <copyright-section>
        <section-block type="copyright_b_3" index="1">
          <ac_copyright-line>
            <isbn>978-1-338-65167-6</isbn>. TM ® &amp; © Scholastic Inc. All rights reserved. © Kotenko Oleksandr/Shutterstock.</ac_copyright-line>
        </section-block>
      </copyright-section>
    </ac_card-3_back>
  </ac_card-3>
  <ac_card-4 day="3">
    <ac_card-4_front>
      <graphic href="EC3-5_AC_Eng_Lang_T3W02D3_C4_01_1295482942_cropped.png"/>
    </ac_card-4_front>
    <ac_card-4_back>
      <masthead>
        <section-block type="masthead_b_4" index="1">
          <ac_header-game-card>WHAT DO CLOUDS MAKE?  </ac_header-game-card>
        </section-block>
      </masthead>
      <ask-section>
        <section-block type="ask_b_4" index="1">
          <ac_ask-extend-hed>Ask</ac_ask-extend-hed>
          <ac_game_card-teacher-talk-white>Is this a picture of warm rain or freezing rain? </ac_game_card-teacher-talk-white>
        </section-block>
      </ask-section>
      <support-section>
        <section-block type="support_b_4" index="1">
          <ac_support-challenge-hed>Support</ac_support-challenge-hed>
          <ac_game_card-teacher-talk-solid>This is a picture of fr<fill-in-the-blank>                  </fill-in-the-blank> <ac_teacher-talk-emphasis_non-ital>(freezing)</ac_teacher-talk-emphasis_non-ital> rain, which is called sleet.</ac_game_card-teacher-talk-solid>
        </section-block>
      </support-section>
      <challenge-section>
        <section-block type="challenge_b_4" index="1">
          <ac_support-challenge-hed>Challenge</ac_support-challenge-hed>
          <ac_game_card-teacher-talk-solid>How is sleet different from warm rain? How is sleet different from snow?</ac_game_card-teacher-talk-solid>
        </section-block>
      </challenge-section>
      <extend-section>
        <section-block type="extend_b_4" index="1">
          <ac_ask-extend-hed>Extend</ac_ask-extend-hed>
          <ac_game_card-teacher-talk-white>Can it be hot outside when we have sleet? Can it be hot outside when it rains?</ac_game_card-teacher-talk-white>
        </section-block>
      </extend-section>
      <copyright-section>
        <section-block type="copyright_b_4" index="1">
          <ac_copyright-line>
            <isbn>978-1-338-65167-6</isbn>. TM ® &amp; © Scholastic Inc. All rights reserved. © Lenush/Shutterstock.</ac_copyright-line>
        </section-block>
      </copyright-section>
    </ac_card-4_back>
  </ac_card-4>
</activity-cards>
