<?xml version="1.0" encoding="UTF-8"?>
<vocabulary-card lang="es">
  <vc_card-1 day="1">
    <vc_card-1_front>
      <graphic href="EC3-5_VC_Eng_Lit_T4W02D1_C01_01_553929166_cropped.png"/>
      <section-block type="f_1" index="1">
        <vc_front_vocab-word>disparado</vc_front_vocab-word>
      </section-block>
    </vc_card-1_front>
    <vc_card-1_back>
      <masthead>
        <section-block type="masthead_b_1" index="1">
          <vc_back_component_header>vocabulario</vc_back_component_header>
        </section-block>
      </masthead>
      <introduce-section>
        <section-block type="introduce_b_1" index="1">
          <vc_back_b-hed_horiz>disparado   </vc_back_b-hed_horiz>
          <vc_back_c-hed>Repita</vc_back_c-hed>
          <vc_back_teacher-talk>Repitan esta palabra: <vc_teacher-talk-emphasis_non-ital>disparado</vc_teacher-talk-emphasis_non-ital>.</vc_back_teacher-talk>
          <vc_back_c-hed>Defina </vc_back_c-hed>
          <vc_back_teacher-talk>Si algo o alguien sale disparado, va muy rápido.</vc_back_teacher-talk>
          <vc_back_c-hed>Describa </vc_back_c-hed>
          <vc_back_teacher-talk>El perro salió disparado. El perro corrió muy rápido.</vc_back_teacher-talk>
          <vc_back_c-hed>Represente</vc_back_c-hed>
          <vc_back_teacher-talk>Simulemos que nuestra mano es un perro que pasa disparado. ¿Listos? ¡Ahí va!  </vc_back_teacher-talk>
        </section-block>
      </introduce-section>
      <reteach-section>
        <section-block type="reteach_b_1" index="1">
          <vc_back_b-hed_horiz>disparado   </vc_back_b-hed_horiz>
          <vc_back_c-hed>Repita</vc_back_c-hed>
          <vc_back_teacher-talk>Repitan esta palabra: <vc_teacher-talk-emphasis_non-ital>disparado</vc_teacher-talk-emphasis_non-ital>.</vc_back_teacher-talk>
          <vc_back_c-hed>Defina </vc_back_c-hed>
          <vc_back_teacher-talk>Si algo o alguien sale disparado, va muy rápido.</vc_back_teacher-talk>
          <vc_back_c-hed>Converse </vc_back_c-hed>
          <vc_back_teacher-talk>Miren la imagen. El perro pasó disparado. ¿Qué cosas pueden pasar o salir disparadas? </vc_back_teacher-talk>
          <vc_teacher-card_body>Repita, reformule o amplíe.</vc_teacher-card_body>
        </section-block>
      </reteach-section>
      <copyright-section>
        <section-block type="copyright_b_1" index="1">
          <vc_back_copyright-line>
            <isbn>978-1-338-64345-9</isbn>. TM ® &amp; © Scholastic Inc. All rights reserved. © OlgaOvcharenko/Shutterstock.</vc_back_copyright-line>
        </section-block>
      </copyright-section>
    </vc_card-1_back>
  </vc_card-1>
  <vc_card-2 day="1">
    <vc_card-2_front>
      <graphic href="EC3-5_VC_Eng_Lit_T4W02D1_C02_01_1335203318_cropped.png"/>
      <section-block type="f_2" index="1">
        <vc_front_vocab-word>rejilla</vc_front_vocab-word>
      </section-block>
    </vc_card-2_front>
    <vc_card-2_back>
      <masthead>
        <section-block type="masthead_b_2" index="1">
          <vc_back_component_header>vocabulario</vc_back_component_header>
        </section-block>
      </masthead>
      <introduce-section>
        <section-block type="introduce_b_2" index="1">
          <vc_back_b-hed>rejilla   </vc_back_b-hed>
          <vc_back_c-hed>Repita</vc_back_c-hed>
          <vc_back_teacher-talk>Repitan esta palabra: <vc_teacher-talk-emphasis_non-ital>rejilla</vc_teacher-talk-emphasis_non-ital>.</vc_back_teacher-talk>
          <vc_back_c-hed>Defina </vc_back_c-hed>
          <vc_back_teacher-talk>Se coloca una rejilla delante de una puerta o ventana para que los insectos no entren cuando está abierta.</vc_back_teacher-talk>
          <vc_back_c-hed>Describa </vc_back_c-hed>
          <vc_back_teacher-talk>El gato mira a través de la rejilla. No puede salir a través de la rejilla.</vc_back_teacher-talk>
          <vc_back_c-hed>Represente</vc_back_c-hed>
          <vc_back_teacher-talk>Simulemos que somos insectos y tratamos de entrar volando. Bzzz...  </vc_back_teacher-talk>
        </section-block>
      </introduce-section>
      <reteach-section>
        <section-block type="reteach_b_2" index="1">
          <vc_back_b-hed>rejilla   </vc_back_b-hed>
          <vc_back_c-hed>Repita</vc_back_c-hed>
          <vc_back_teacher-talk>Repitan esta palabra: <vc_teacher-talk-emphasis_non-ital>rejilla</vc_teacher-talk-emphasis_non-ital>.</vc_back_teacher-talk>
          <vc_back_c-hed>Defina </vc_back_c-hed>
          <vc_back_teacher-talk>Se coloca una rejilla delante de una puerta o ventana para que los insectos no entren cuando está abierta.</vc_back_teacher-talk>
          <vc_back_c-hed>Converse </vc_back_c-hed>
          <vc_back_teacher-talk>Miren la imagen. El gato mira a través de la rejilla. ¿Por qué los insectos no pueden volar a través de la rejilla?</vc_back_teacher-talk>
          <vc_teacher-card_body>Repita, reformule o amplíe.</vc_teacher-card_body>
        </section-block>
      </reteach-section>
      <copyright-section>
        <section-block type="copyright_b_2" index="1">
          <vc_back_copyright-line>
            <isbn>978-1-338-64345-9</isbn>. TM ® &amp; © Scholastic Inc. All rights reserved. © domonku/Shutterstock.</vc_back_copyright-line>
        </section-block>
      </copyright-section>
    </vc_card-2_back>
  </vc_card-2>
  <vc_card-3 day="2">
    <vc_card-3_front>
      <graphic href="EC3-5_VC_Eng_Lit_T4W02D2_C01_01_160162838_cropped.png"/>
      <section-block type="f_3" index="1">
        <vc_front_vocab-word>sentimientos</vc_front_vocab-word>
      </section-block>
    </vc_card-3_front>
    <vc_card-3_back>
      <masthead>
        <section-block type="masthead_b_3" index="1">
          <vc_back_component_header>vocabulario</vc_back_component_header>
        </section-block>
      </masthead>
      <introduce-section>
        <section-block type="introduce_b_3" index="1">
          <vc_back_b-hed>sentimientos   </vc_back_b-hed>
          <vc_back_c-hed>Repita</vc_back_c-hed>
          <vc_back_teacher-talk>Repitan esta palabra: <vc_teacher-talk-emphasis_non-ital>sentimientos</vc_teacher-talk-emphasis_non-ital>.</vc_back_teacher-talk>
          <vc_back_c-hed>Defina </vc_back_c-hed>
          <vc_back_teacher-talk>Los sentimientos dicen cómo nos sentimos, por ejemplo, felices, tristes, enojados, asustados o entusiasmados.</vc_back_teacher-talk>
          <vc_back_c-hed>Describa </vc_back_c-hed>
          <vc_back_teacher-talk>La niña y su perro están mostrando sus sentimientos. </vc_back_teacher-talk>
          <vc_back_c-hed>Represente</vc_back_c-hed>
          <vc_back_teacher-talk>Vamos a mostrar nuestros sentimientos. Simulemos que estamos felices. Simulemos que estamos tristes. ¡Simulemos que estamos entusiasmados!  </vc_back_teacher-talk>
        </section-block>
      </introduce-section>
      <reteach-section>
        <section-block type="reteach_b_3" index="1">
          <vc_back_b-hed>sentimientos   </vc_back_b-hed>
          <vc_back_c-hed>Repita</vc_back_c-hed>
          <vc_back_teacher-talk>Repitan esta palabra: <vc_teacher-talk-emphasis_non-ital>sentimientos</vc_teacher-talk-emphasis_non-ital>.</vc_back_teacher-talk>
          <vc_back_c-hed>Defina </vc_back_c-hed>
          <vc_back_teacher-talk>Los sentimientos dicen cómo nos sentimos, por ejemplo, felices, tristes, enojados, asustados o entusiasmados.</vc_back_teacher-talk>
          <vc_back_c-hed>Converse </vc_back_c-hed>
          <vc_back_teacher-talk>Miren la imagen. La niña y su perro muestran sus sentimientos. ¿Cómo creen que se sienten? </vc_back_teacher-talk>
          <vc_teacher-card_body>Repita, reformule o amplíe.</vc_teacher-card_body>
        </section-block>
      </reteach-section>
      <copyright-section>
        <section-block type="copyright_b_3" index="1">
          <vc_back_copyright-line>
            <isbn>978-1-338-64345-9</isbn>. TM ® &amp; © Scholastic Inc. All rights reserved. © Ermolaev Alexander/Shutterstock.</vc_back_copyright-line>
        </section-block>
      </copyright-section>
    </vc_card-3_back>
  </vc_card-3>
  <vc_card-4 day="2">
    <vc_card-4_front>
      <graphic href="EC3-5_VC_Eng_Lit_T4W02D2_C02_01_424218274_cropped.png"/>
      <section-block type="f_4" index="1">
        <vc_front_vocab-word>disgustaba</vc_front_vocab-word>
      </section-block>
    </vc_card-4_front>
    <vc_card-4_back>
      <masthead>
        <section-block type="masthead_b_4" index="1">
          <vc_back_component_header>vocabulario</vc_back_component_header>
        </section-block>
      </masthead>
      <introduce-section>
        <section-block type="introduce_b_4" index="1">
          <vc_back_b-hed>disgustaba   </vc_back_b-hed>
          <vc_back_c-hed>Repita</vc_back_c-hed>
          <vc_back_teacher-talk>Repitan esta palabra: <vc_teacher-talk-emphasis_non-ital>disgustaba</vc_teacher-talk-emphasis_non-ital>.</vc_back_teacher-talk>
          <vc_back_c-hed>Defina </vc_back_c-hed>
          <vc_back_teacher-talk>Cuando a alguien le disgustaba algo, no le gustaba para nada.</vc_back_teacher-talk>
          <vc_back_c-hed>Describa </vc_back_c-hed>
          <vc_back_teacher-talk>Al perro le disgusta la comida que tiene delante. El perro no come la comida.</vc_back_teacher-talk>
          <vc_back_c-hed>Represente</vc_back_c-hed>
          <vc_back_teacher-talk>Simulemos que nos dan algo que no nos gusta. Levantemos las manos. ¡No, gracias!  </vc_back_teacher-talk>
        </section-block>
      </introduce-section>
      <reteach-section>
        <section-block type="reteach_b_4" index="1">
          <vc_back_b-hed>disgustaba  </vc_back_b-hed>
          <vc_back_c-hed>Repita</vc_back_c-hed>
          <vc_back_teacher-talk>Repitan esta palabra: <vc_teacher-talk-emphasis_non-ital>disgustaba</vc_teacher-talk-emphasis_non-ital>.</vc_back_teacher-talk>
          <vc_back_c-hed>Defina </vc_back_c-hed>
          <vc_back_teacher-talk>Cuando a alguien le disgustaba algo, no le gustaba para nada.</vc_back_teacher-talk>
          <vc_back_c-hed>Converse </vc_back_c-hed>
          <vc_back_teacher-talk>¿Qué comida les disgusta a ustedes?</vc_back_teacher-talk>
          <vc_teacher-card_body>Repita, reformule o amplíe.</vc_teacher-card_body>
        </section-block>
      </reteach-section>
      <copyright-section>
        <section-block type="copyright_b_4" index="1">
          <vc_back_copyright-line>
            <isbn>978-1-338-64345-9</isbn>. TM ® &amp; © Scholastic Inc. All rights reserved. © Chaisit Rattanachusri/Shutterstock.</vc_back_copyright-line>
        </section-block>
      </copyright-section>
    </vc_card-4_back>
  </vc_card-4>
  <vc_card-5 day="3">
    <vc_card-5_front>
      <graphic href="EC3-5_VC_Eng_Lit_T4W02D3_C01_01___57325591_cropped.png"/>
      <section-block type="f_5" index="1">
        <vc_front_vocab-word>marca de comprobación</vc_front_vocab-word>
      </section-block>
    </vc_card-5_front>
    <vc_card-5_back>
      <masthead>
        <section-block type="masthead_b_5" index="1">
          <vc_back_component_header>vocabulario</vc_back_component_header>
        </section-block>
      </masthead>
      <introduce-section>
        <section-block type="introduce_b_5" index="1">
          <vc_back_b-hed>marca de comprobación   </vc_back_b-hed>
          <vc_back_c-hed>Repita</vc_back_c-hed>
          <vc_back_teacher-talk>Repitan estas palabras: <vc_teacher-talk-emphasis_non-ital>marca de comprobación</vc_teacher-talk-emphasis_non-ital>.</vc_back_teacher-talk>
          <vc_back_c-hed>Defina </vc_back_c-hed>
          <vc_back_teacher-talk>Una marca de comprobación es una marca que se hace en una casilla cuando se completa o se hace algo.</vc_back_teacher-talk>
          <vc_back_c-hed>Describa </vc_back_c-hed>
          <vc_back_teacher-talk>Estas marcas de comprobación muestran qué útiles tenemos.</vc_back_teacher-talk>
          <vc_back_c-hed>Represente</vc_back_c-hed>
          <vc_back_teacher-talk>Simulemos que hacemos una marca de comprobación en el aire. ¿Listos? ¡Comprobado!  </vc_back_teacher-talk>
        </section-block>
      </introduce-section>
      <reteach-section>
        <section-block type="reteach_b_5" index="1">
          <vc_back_b-hed>marca de comprobación   </vc_back_b-hed>
          <vc_back_c-hed>Repita</vc_back_c-hed>
          <vc_back_teacher-talk>Repitan estas palabras: <vc_teacher-talk-emphasis_non-ital>marca de comprobación</vc_teacher-talk-emphasis_non-ital>.</vc_back_teacher-talk>
          <vc_back_c-hed>Defina </vc_back_c-hed>
          <vc_back_teacher-talk>Una marca de comprobación es una marca que se hace en una casilla cuando se completa o se hace algo.</vc_back_teacher-talk>
          <vc_back_c-hed>Converse </vc_back_c-hed>
          <vc_back_teacher-talk>En la imagen las casillas tiene marcas de comprobación. ¿Alguna vez usaron marcas como estas?</vc_back_teacher-talk>
          <vc_teacher-card_body>Repita, reformule o amplíe.</vc_teacher-card_body>
        </section-block>
      </reteach-section>
      <copyright-section>
        <section-block type="copyright_b_5" index="1">
          <vc_back_copyright-line>
            <isbn>978-1-338-64345-9</isbn>. TM ® &amp; © Scholastic Inc. All rights reserved. © Feng Yu/Shutterstock.</vc_back_copyright-line>
        </section-block>
      </copyright-section>
    </vc_card-5_back>
  </vc_card-5>
  <vc_card-6 day="4">
    <vc_card-6_front>
      <graphic href="EC3-5_VC_Eng_Lit_T4W02D4_C01_01_511242844_cropped.png"/>
      <section-block type="f_6" index="1">
        <vc_front_vocab-word>mascotas</vc_front_vocab-word>
      </section-block>
    </vc_card-6_front>
    <vc_card-6_back>
      <masthead>
        <section-block type="masthead_b_6" index="1">
          <vc_back_component_header>vocabulario</vc_back_component_header>
        </section-block>
      </masthead>
      <introduce-section>
        <section-block type="introduce_b_6" index="1">
          <vc_back_b-hed>mascotas   </vc_back_b-hed>
          <vc_back_c-hed>Repita</vc_back_c-hed>
          <vc_back_teacher-talk>Repitan esta palabra: <vc_teacher-talk-emphasis_non-ital>mascotas</vc_teacher-talk-emphasis_non-ital>.</vc_back_teacher-talk>
          <vc_back_c-hed>Defina </vc_back_c-hed>
          <vc_back_teacher-talk>Las mascotas son animales que las personas tienen en casa y a los que cuidan.</vc_back_teacher-talk>
          <vc_back_c-hed>Describa </vc_back_c-hed>
          <vc_back_teacher-talk>La niña está cargando a su gato. El gato de la niña es su mascota.</vc_back_teacher-talk>
          <vc_back_c-hed>Represente</vc_back_c-hed>
          <vc_back_teacher-talk>Simulemos que estamos cargando a nuestras mascotas. ¿Es grande o pequeña? ¡Muéstrenme con sus brazos! </vc_back_teacher-talk>
        </section-block>
      </introduce-section>
      <reteach-section>
        <section-block type="reteach_b_6" index="1">
          <vc_back_b-hed>mascotas   </vc_back_b-hed>
          <vc_back_c-hed>Repita</vc_back_c-hed>
          <vc_back_teacher-talk>Repitan esta palabra: <vc_teacher-talk-emphasis_non-ital>mascotas</vc_teacher-talk-emphasis_non-ital>.</vc_back_teacher-talk>
          <vc_back_c-hed>Defina </vc_back_c-hed>
          <vc_back_teacher-talk>Las mascotas son animales que las personas tienen en casa y a los que cuidan.</vc_back_teacher-talk>
          <vc_back_c-hed>Converse </vc_back_c-hed>
          <vc_back_teacher-talk>En la imagen, la niña está cargando a su gatito. ¿Pueden nombrar otras mascotas? </vc_back_teacher-talk>
          <vc_teacher-card_body>Repita, reformule o amplíe.</vc_teacher-card_body>
        </section-block>
      </reteach-section>
      <copyright-section>
        <section-block type="copyright_b_6" index="1">
          <vc_back_copyright-line>
            <isbn>978-1-338-64345-9</isbn>. TM ® &amp; © Scholastic Inc. All rights reserved. © Ronnachai Palas/Shutterstock.</vc_back_copyright-line>
        </section-block>
      </copyright-section>
    </vc_card-6_back>
  </vc_card-6>
  <vc_card-7 day="4">
    <vc_card-7_front>
      <graphic href="EC3-5_VC_Eng_Lit_T4W02D4_C02_01_1138198052_cropped.png"/>
      <section-block type="f_7" index="1">
        <vc_front_vocab-word>ejercicio</vc_front_vocab-word>
      </section-block>
    </vc_card-7_front>
    <vc_card-7_back>
      <masthead>
        <section-block type="masthead_b_7" index="1">
          <vc_back_component_header>vocabulario</vc_back_component_header>
        </section-block>
      </masthead>
      <introduce-section>
        <section-block type="introduce_b_7" index="1">
          <vc_back_b-hed_horiz>ejercicio   </vc_back_b-hed_horiz>
          <vc_back_c-hed>Repita</vc_back_c-hed>
          <vc_back_teacher-talk>Repitan esta palabra: <vc_teacher-talk-emphasis_non-ital>ejercicio</vc_teacher-talk-emphasis_non-ital>.</vc_back_teacher-talk>
          <vc_back_c-hed>Defina </vc_back_c-hed>
          <vc_back_teacher-talk>Hacer ejercicio significa mover el cuerpo de manera que nos mantengamos fuertes y saludables.</vc_back_teacher-talk>
          <vc_back_c-hed>Describa </vc_back_c-hed>
          <vc_back_teacher-talk>A este niño y a su perro les gusta hacer ejercicio. El niño y el perro corren juntos.</vc_back_teacher-talk>
          <vc_back_c-hed>Represente</vc_back_c-hed>
          <vc_back_teacher-talk>¡Hagamos ejercicio ahora mismo! Vamos a pararnos y a estirarnos. Caminemos sin movernos del sitio. Demos un salto. ¡Nos encanta hacer ejercicio!  </vc_back_teacher-talk>
        </section-block>
      </introduce-section>
      <reteach-section>
        <section-block type="reteach_b_7" index="1">
          <vc_back_b-hed_horiz>ejercicio   </vc_back_b-hed_horiz>
          <vc_back_c-hed>Repita</vc_back_c-hed>
          <vc_back_teacher-talk_horiz>Repitan esta palabra: <vc_teacher-talk-emphasis_non-ital>ejercicio</vc_teacher-talk-emphasis_non-ital>.</vc_back_teacher-talk_horiz>
          <vc_back_c-hed>Defina </vc_back_c-hed>
          <vc_back_teacher-talk>Hacer ejercicio significa mover el cuerpo de manera que nos mantengamos fuertes y saludables.</vc_back_teacher-talk>
          <vc_back_c-hed>Converse </vc_back_c-hed>
          <vc_back_teacher-talk>Miren la imagen. Al niño y a su perro les gusta hacer ejercicio. ¿Qué tanto les gusta hacer ejercicio a ustedes?</vc_back_teacher-talk>
          <vc_teacher-card_body>Repita, reformule o amplíe.</vc_teacher-card_body>
        </section-block>
      </reteach-section>
      <copyright-section>
        <section-block type="copyright_b_7" index="1">
          <vc_back_copyright-line>
            <isbn>978-1-338-64345-9</isbn>. TM ® &amp; © Scholastic Inc. All rights reserved. © mustafagull/Getty Images.</vc_back_copyright-line>
        </section-block>
      </copyright-section>
    </vc_card-7_back>
  </vc_card-7>
  <vc_card-8 day="5">
    <vc_card-8_front>
      <graphic href="EC3-5_VC_Spa_Lit_T4W02D5_C01_01_1512544892_cropped.png"/>
      <section-block type="f_8" index="1">
        <vc_front_vocab-word>garras</vc_front_vocab-word>
      </section-block>
    </vc_card-8_front>
    <vc_card-8_back>
      <masthead>
        <section-block type="masthead_b_8" index="1">
          <vc_back_component_header>vocabulario</vc_back_component_header>
        </section-block>
      </masthead>
      <introduce-section>
        <section-block type="introduce_b_8" index="1">
          <vc_back_b-hed_horiz>garras    </vc_back_b-hed_horiz>
          <vc_back_c-hed>Repita</vc_back_c-hed>
          <vc_back_teacher-talk>Repitan esta palabra: <vc_teacher-talk-emphasis_non-ital>garras</vc_teacher-talk-emphasis_non-ital>.</vc_back_teacher-talk>
          <vc_back_c-hed>Defina </vc_back_c-hed>
          <vc_back_teacher-talk>Las garras son las manos o los pies de algunos animales con uñas fuertes y curvadas.</vc_back_teacher-talk>
          <vc_back_c-hed>Describa </vc_back_c-hed>
          <vc_back_teacher-talk>El gato usa las garras para subir al árbol. Las garras del gato son muy fuertes.</vc_back_teacher-talk>
          <vc_back_c-hed>Represente</vc_back_c-hed>
          <vc_back_teacher-talk>Simulemos que tenemos garras. Abran la mano, separen los dedos y luego dóblenlos hacia adelante. ¡Muestren como usan las garras para subir a un árbol! </vc_back_teacher-talk>
        </section-block>
      </introduce-section>
      <reteach-section>
        <section-block type="reteach_b_8" index="1">
          <vc_back_b-hed_horiz>garras   </vc_back_b-hed_horiz>
          <vc_back_c-hed>Repita</vc_back_c-hed>
          <vc_back_teacher-talk>Repitan esta palabra: <vc_teacher-talk-emphasis_non-ital>garras</vc_teacher-talk-emphasis_non-ital>.</vc_back_teacher-talk>
          <vc_back_c-hed>Defina </vc_back_c-hed>
          <vc_back_teacher-talk>Las garras son las manos o los pies de algunos animales con uñas fuertes y curvadas.</vc_back_teacher-talk>
          <vc_back_c-hed>Converse </vc_back_c-hed>
          <vc_back_teacher-talk>Miren la imagen. Las garras del gato lo ayudan a subir al árbol. ¿Pueden decir otro animal que tenga garras?</vc_back_teacher-talk>
          <vc_teacher-card_body>Repita, reformule o amplíe.</vc_teacher-card_body>
        </section-block>
      </reteach-section>
      <copyright-section>
        <section-block type="copyright_b_8" index="1">
          <vc_back_copyright-line>
            <isbn>978-1-338-64345-9</isbn>. TM ® &amp; © Scholastic Inc. All rights reserved. © Kamolthip Katutat/Shutterstock.</vc_back_copyright-line>
        </section-block>
      </copyright-section>
    </vc_card-8_back>
  </vc_card-8>
</vocabulary-card>
